datasalad/__init__.py
datasalad/_version.py
datasalad/py.typed
datasalad/gitpathspec/__init__.py
datasalad/gitpathspec/pathspec.py
datasalad/gitpathspec/pathspecs.py
datasalad/gitpathspec/tests/__init__.py
datasalad/gitpathspec/tests/test_gitpathspec.py
datasalad/iterable_subprocess/LICENSE
datasalad/iterable_subprocess/README.md
datasalad/iterable_subprocess/__init__.py
datasalad/iterable_subprocess/iterable_subprocess.py
datasalad/iterable_subprocess/pyproject.toml
datasalad/iterable_subprocess/test_iterable_subprocess.py
datasalad/itertools/__init__.py
datasalad/itertools/align_pattern.py
datasalad/itertools/decode_bytes.py
datasalad/itertools/itemize.py
datasalad/itertools/load_json.py
datasalad/itertools/reroute.py
datasalad/itertools/tests/__init__.py
datasalad/itertools/tests/test_align_pattern.py
datasalad/itertools/tests/test_decode_bytes.py
datasalad/itertools/tests/test_itemize.py
datasalad/itertools/tests/test_load_json.py
datasalad/itertools/tests/test_reroute.py
datasalad/runners/__init__.py
datasalad/runners/exception.py
datasalad/runners/iter_subproc.py
datasalad/runners/tests/__init__.py
datasalad/runners/tests/test_exception.py
datasalad/runners/tests/test_iter_subproc.py
datasalad/settings/__init__.py
datasalad/settings/defaults.py
datasalad/settings/env.py
datasalad/settings/setting.py
datasalad/settings/settings.py
datasalad/settings/source.py
datasalad/settings/tests/__init__.py
datasalad/settings/tests/test_defaults.py
datasalad/settings/tests/test_env.py
datasalad/settings/tests/test_setting.py
datasalad/settings/tests/test_settings.py
datasalad/settings/tests/test_source.py
datasalad/tests/__init__.py
datasalad/tests/fixtures.py
datasalad-0.6.0.dist-info/METADATA
datasalad-0.6.0.dist-info/WHEEL
datasalad-0.6.0.dist-info/licenses/LICENSE
datasalad-0.6.0.dist-info/RECORD
