Metadata-Version: 2.4
Name: datasalad
Version: 0.6.0
Summary: utilities for working with data in the vicinity of Git and git-annex
Project-URL: Homepage, https://github.com/datalad/datasalad
Project-URL: Documentation, https://github.com/datalad/datasalad#readme
Project-URL: Issues, https://github.com/datalad/datasalad/issues
Project-URL: Source, https://github.com/datalad/datasalad
Project-URL: Changelog, https://github.com/datalad/datasalad/blob/main/CHANGELOG.md
Author-email: Michael Hanke <michael.hanke@gmail.com>
Maintainer-email: Michael Hanke <michael.hanke@gmail.com>
License-Expression: MIT
License-File: LICENSE
Keywords: datalad,git,git-annex,iterator,subprocess
Classifier: Development Status :: 4 - Beta
Classifier: Intended Audience :: Developers
Classifier: Intended Audience :: End Users/Desktop
Classifier: License :: OSI Approved :: MIT License
Classifier: Natural Language :: English
Classifier: Operating System :: OS Independent
Classifier: Programming Language :: Python
Classifier: Programming Language :: Python :: 3
Classifier: Programming Language :: Python :: 3.9
Classifier: Programming Language :: Python :: 3.10
Classifier: Programming Language :: Python :: 3.11
Classifier: Programming Language :: Python :: 3.12
Classifier: Programming Language :: Python :: 3.13
Classifier: Programming Language :: Python :: Implementation :: CPython
Classifier: Programming Language :: Python :: Implementation :: PyPy
Classifier: Topic :: Software Development
Classifier: Topic :: Software Development :: Version Control
Classifier: Topic :: Software Development :: Version Control :: Git
Requires-Python: >=3.9
Provides-Extra: docs
Requires-Dist: sphinx; extra == 'docs'
Requires-Dist: sphinx-rtd-theme; extra == 'docs'
